{
  "/_not-found/page": "app/_not-found/page.js",
  "/logout/route": "app/logout/route.js",
  "/crypto/page": "app/crypto/page.js",
  "/delphic-signals/page": "app/delphic-signals/page.js",
  "/dashboard/page": "app/dashboard/page.js",
  "/login/page": "app/login/page.js",
  "/page": "app/page.js",
  "/performance/page": "app/performance/page.js",
  "/home/page": "app/home/page.js",
  "/proposte/page": "app/proposte/page.js",
  "/segnali-wall-street/page": "app/segnali-wall-street/page.js",
  "/radar/page": "app/radar/page.js"
}